neptune_wrapper/__init__.py
neptune_wrapper/utils.py
neptune_wrapper/wrapper.py
neptune_wrapper-0.1.0.dist-info/LICENSE
neptune_wrapper-0.1.0.dist-info/METADATA
neptune_wrapper-0.1.0.dist-info/WHEEL
neptune_wrapper-0.1.0.dist-info/top_level.txt
neptune_wrapper-0.1.0.dist-info/RECORD
