Metadata-Version: 2.1
Name: neptune-wrapper
Version: 0.1.0
Summary: OS-independent wrapper for the Neptune.ai API
Author-email: bryzgalovdm <bryzgalovdm@gmail.com>
License: GNU GENERAL PUBLIC LICENSE
Project-URL: Homepage, https://github.com/bryzgalovdm/neptune_wrapper
Keywords: machine learning,experiment tracking
Classifier: License :: OSI Approved :: GNU General Public License v3 or later (GPLv3+)
Classifier: Programming Language :: Python
Classifier: Programming Language :: Python :: 3
Requires-Python: >=3.10
License-File: LICENSE
Requires-Dist: neptune >=1.5
Requires-Dist: neptune-pytorch >=2
Requires-Dist: neptune-tensorflow-keras
Requires-Dist: pathlib
Provides-Extra: dev
Requires-Dist: pytest ; extra == 'dev'
